youtube_audio_collector/__init__.py
youtube_audio_collector/__main__.py
youtube_audio_collector/cli.py
youtube_audio_collector/config.py
youtube_audio_collector/exceptions.py
youtube_audio_dataset_collector-0.1.5.dist-info/licenses/LICENSE
youtube_audio_dataset_collector-0.1.5.dist-info/METADATA
youtube_audio_dataset_collector-0.1.5.dist-info/WHEEL
youtube_audio_dataset_collector-0.1.5.dist-info/top_level.txt
youtube_audio_dataset_collector-0.1.5.dist-info/RECORD
