Metadata-Version: 2.4
Name: youtube-audio-dataset-collector
Version: 0.1.5
Summary: A comprehensive tool for downloading, processing, and transcribing audio from YouTube videos and playlists for machine learning datasets
Author: Ranjan Shettigar
Author-email: Ranjan Shettigar <theloko.dev@gmail.com>
License: MIT
Requires-Python: >=3.8
License-File: LICENSE
Requires-Dist: yt-dlp>=2023.1.6
Requires-Dist: pydub>=0.25.1
Requires-Dist: google-generativeai>=0.3.0
Requires-Dist: python-dotenv>=0.19.0
Requires-Dist: tqdm>=4.64.0
Requires-Dist: numpy>=1.21.0
Requires-Dist: soundfile>=0.12.1
Dynamic: author
Dynamic: license-file
Dynamic: requires-python
